wardengui/__init__.py
wardengui/__main__.py
wardengui/cli.py
wardengui/colors.py
wardengui/system_test.py
wardengui/warden.py
wardengui-1.0.19.dist-info/licenses/LICENSE
wardengui-1.0.19.dist-info/METADATA
wardengui-1.0.19.dist-info/WHEEL
wardengui-1.0.19.dist-info/entry_points.txt
wardengui-1.0.19.dist-info/top_level.txt
wardengui-1.0.19.dist-info/RECORD
