Metadata-Version: 2.4
Name: wardengui
Version: 1.0.19
Summary: A terminal GUI for managing Warden Docker environments
Author-email: Yehor Shytikov <yehor@example.com>
Project-URL: Homepage, https://github.com/Genaker/WardenGUI
Project-URL: Repository, https://github.com/Genaker/WardenGUI
Keywords: warden,docker,gui,terminal,development,environment
Classifier: Development Status :: 4 - Beta
Classifier: Environment :: Console
Classifier: Intended Audience :: Developers
Classifier: License :: OSI Approved :: MIT License
Classifier: Operating System :: OS Independent
Classifier: Programming Language :: Python :: 3
Classifier: Programming Language :: Python :: 3.8
Classifier: Programming Language :: Python :: 3.9
Classifier: Programming Language :: Python :: 3.10
Classifier: Programming Language :: Python :: 3.11
Classifier: Programming Language :: Python :: 3.12
Classifier: Topic :: Software Development :: Build Tools
Classifier: Topic :: System :: Systems Administration
Requires-Python: >=3.8
License-File: LICENSE
Provides-Extra: test
Requires-Dist: pytest>=7.0.0; extra == "test"
Requires-Dist: pytest-cov>=4.0.0; extra == "test"
Dynamic: license-file
